<?xml version="1.0" encoding="UTF-8"?>  

<Defs>

<!--__Helmets__-->

<!-- MI Scout Helmet -->

<ThingDef ParentName="ArmorHelmetMakeableBase">
    <defName>Fed_Apparel_MIScoutHelmet</defName>
    <label>MI Scout Helmet</label>
    <description>"The MI Scout Helmet prioritizes awareness over armor. Its advanced HUD feeds real-time tactical data directly to your retina while maintaining minimal weight. Reconnaissance troopers swear by the Scout helmet's superior field of view—when you need to see them before they see you, this is what you wear."</description>
    <techLevel>Spacer</techLevel>
    <graphicData>
      <texPath>Things/Items/Apparel/MIMobileInfantryHelmet_south</texPath>
      <graphicClass>Graphic_Single</graphicClass>
    </graphicData>
    <uiIconScale>1.4</uiIconScale>
    <stuffCategories>
      <li>Metallic</li>
    </stuffCategories>
    <costStuffCount>40</costStuffCount>
    <tradeTags>
      <li>Clothing</li>
      <li>Armor</li>
    </tradeTags>
    <statBases>
      <WorkToMake>3200</WorkToMake>
      <MaxHitPoints>100</MaxHitPoints>
      <Mass>2</Mass>
      <ArmorRating_Sharp>1.00</ArmorRating_Sharp>
      <ArmorRating_Blunt>0.36</ArmorRating_Blunt>
      <ArmorRating_Heat>0.27</ArmorRating_Heat>
      <StuffEffectMultiplierArmor>0.5</StuffEffectMultiplierArmor>
      <StuffEffectMultiplierInsulation_Cold>0.15</StuffEffectMultiplierInsulation_Cold>
      <StuffEffectMultiplierInsulation_Heat>0</StuffEffectMultiplierInsulation_Heat>
      <EquipDelay>1.5</EquipDelay>
    </statBases>
    <recipeMaker>
      <researchPrerequisite>Research_FederationArmory</researchPrerequisite>
      <recipeUsers>
        <li>ElectricSmithy</li>
        <li>FueledSmithy</li>
      </recipeUsers>
      <displayPriority>200</displayPriority>
    </recipeMaker>
    <apparel>
      <countsAsClothingForNudity>false</countsAsClothingForNudity>
      <bodyPartGroups>
        <li>UpperHead</li>
      </bodyPartGroups>
      <wornGraphicPath>Things/Items/Apparel/MIMobileInfantryHelmet</wornGraphicPath>
      <layers>
        <li>Overhead</li>
      </layers>
      <tags>
        <li>IndustrialMilitaryBasic</li>
      </tags>
      <defaultOutfitTags>
        <li>Soldier</li>
      </defaultOutfitTags>
    </apparel>
  </ThingDef>
    
<!-- M-1A4 Powered Helmet -->

<ThingDef ParentName="ArmorHelmetMakeableBase">
   <defName>Fed_Apparel_M-1A4PoweredHelmet</defName>
    <label>M-1A4 Powered Helmet</label>
    <description>"The M-1A4 Powered Helmet transforms the trooper's perception of combat. Three-hundred-sixty degree awareness means nothing sneaks up on you—sensors feed visual, thermal, and tactical data directly into your field of view. Targeting reticules lock onto threats automatically. Squad status updates in real-time. This isn't just protection—it's total battlefield domination through information superiority. The helmet's indirect visual system and armored construction can stop rounds that would penetrate standard MI helmets. When sealed with the powered suit body, you're protected from vacuum, hostile atmospheres, and NBC threats."</description>
    <techLevel>Spacer</techLevel>
    <recipeMaker>
      <unfinishedThingDef>UnfinishedTechArmor</unfinishedThingDef>
      <researchPrerequisite>Research_FederationArmory</researchPrerequisite>
      <skillRequirements>
        <Crafting>8</Crafting>
      </skillRequirements>
      <recipeUsers Inherit="False">
        <li>FabricationBench</li>
      </recipeUsers>
    </recipeMaker>
    <graphicData>
      <texPath>Things/Items/Apparel/M-1A4PoweredHelmet_south</texPath>
      <graphicClass>Graphic_Single</graphicClass>
      <drawSize>(0.9, 0.9)</drawSize>
    </graphicData>
    <tradeTags>
      <li>HiTechArmor</li>
      <li>Armor</li>
    </tradeTags>
    <generateCommonality>2</generateCommonality>
    <statBases>
      <WorkToMake>26250</WorkToMake>
      <MaxHitPoints>180</MaxHitPoints>
      <Mass>2</Mass>
      <Flammability>0.4</Flammability>
      <ArmorRating_Sharp>1.2</ArmorRating_Sharp>
      <ArmorRating_Blunt>0.5</ArmorRating_Blunt>
      <ArmorRating_Heat>0.6</ArmorRating_Heat>
      <Insulation_Cold>4</Insulation_Cold>
      <Insulation_Heat>2</Insulation_Heat>
      <EquipDelay>6</EquipDelay>
    </statBases>
    <equippedStatOffsets>
      <ShootingAccuracyPawn>0.2</ShootingAccuracyPawn>
      <VacuumResistance MayRequire="Ludeon.RimWorld.Odyssey">0.68</VacuumResistance>
    </equippedStatOffsets>
    <costList>
      <ComponentSpacer>1</ComponentSpacer>
      <Plasteel>50</Plasteel>
    </costList>
    <apparel>
      <bodyPartGroups>
        <li>FullHead</li>
      </bodyPartGroups>
      <wornGraphicPath>Things/Items/Apparel/M-1A4PoweredHelmet</wornGraphicPath>
      <layers>
        <li>Overhead</li>
      </layers>
      <defaultOutfitTags>
        <li>Soldier</li>
        <li>Spacefarer</li>
      </defaultOutfitTags>
      <useDeflectMetalEffect>true</useDeflectMetalEffect>
    </apparel>
    <comps>
      <li Class="CompProperties_Biocodable"/>
    </comps>
    <thingSetMakerTags>
      <li>RewardStandardHighFreq</li>
    </thingSetMakerTags>
  </ThingDef>
  
<!-- MI Field Cap -->

<ThingDef ParentName="HatMakeableBase">
    <defName>Fed_Apparel_MIFieldCap</defName>
    <label>MI Field Cap</label>
    <description>"The MI field cap is what troopers wear when they're not in combat—during transport to combat zones, garrison duty, or brief moments of downtime. It's not armor, it won't stop a bug, but it keeps the sun out of your eyes and marks you as Mobile Infantry. Some veterans never take it off, even when regulation says otherwise. It's a small comfort in a dangerous galaxy."</description>
    <graphicData>
      <texPath>Things/Items/Apparel/MICombatUndersuitCap_south</texPath>
      <graphicClass>Graphic_Single</graphicClass>
      <shaderType>CutoutComplex</shaderType>
    </graphicData>
    <uiIconScale>1.25</uiIconScale>
    <costStuffCount>20</costStuffCount>
    <stuffCategories>
      <li>Fabric</li>
    </stuffCategories>
    <statBases>
      <MaxHitPoints>80</MaxHitPoints>
      <WorkToMake>1200</WorkToMake>
      <Mass>0.07</Mass>
      <StuffEffectMultiplierArmor>0.2</StuffEffectMultiplierArmor>
      <StuffEffectMultiplierInsulation_Cold>0.50</StuffEffectMultiplierInsulation_Cold>
      <StuffEffectMultiplierInsulation_Heat>0</StuffEffectMultiplierInsulation_Heat>
      <EquipDelay>0.8</EquipDelay>
    </statBases>
    <generateCommonality>0.5</generateCommonality>
    <recipeMaker>
      <researchPrerequisite>Research_FederationArmory</researchPrerequisite>
      <displayPriority>105</displayPriority>
    </recipeMaker>
    <apparel>
      <countsAsClothingForNudity>false</countsAsClothingForNudity>
      <bodyPartGroups>
        <li>UpperHead</li>
      </bodyPartGroups>
      <wornGraphicPath>Things/Items/Apparel/MICombatUndersuitCap</wornGraphicPath>
      <layers>
        <li>Overhead</li>
      </layers>
      <tags>
        <li>Fed_Apparel_MIFieldCap</li>
      </tags>
      <defaultOutfitTags>
        <li>Worker</li>
        <li>Soldier</li>
      </defaultOutfitTags>
      <useWornGraphicMask>true</useWornGraphicMask>
    </apparel>
    <tradeTags>
      <li>BasicClothing</li>
    </tradeTags>
  </ThingDef>

<!--__Armors and Apparels__-->

<!-- MI Scout Body Armor -->

<ThingDef ParentName="ArmorMachineableBase">
    <defName>Fed_Apparel_MIScoutBodyArmor</defName>
    <label>MI Scout Body Armor</label>
    <description>"MI Scout Armor trades heavy plating for speed and agility. Reconnaissance troopers need to move fast, stay quiet, and get out alive—this armor delivers. While it won't stop a plasma bug blast, it'll keep you breathing through small arms fire and let you outrun anything heavier. Move light, move fast, stay alive."</description>
    <techLevel>Spacer</techLevel>
    <recipeMaker>
      <researchPrerequisite>Research_FederationArmory</researchPrerequisite>
      <unfinishedThingDef>UnfinishedTechArmor</unfinishedThingDef>
      <skillRequirements>
        <Crafting>4</Crafting>
      </skillRequirements>
      <displayPriority>220</displayPriority>
    </recipeMaker>
    <graphicData>
      <texPath>Things/Items/Apparel/MIMobileInfantryFlakVest_Male_south</texPath>
      <graphicClass>Graphic_Single</graphicClass>
      <drawSize>1.10</drawSize>
    </graphicData>
    <statBases>
      <WorkToMake>9000</WorkToMake>
      <MaxHitPoints>200</MaxHitPoints>
      <Mass>4</Mass>
      <Flammability>0.6</Flammability>
      <ArmorRating_Sharp>1.00</ArmorRating_Sharp>
      <ArmorRating_Blunt>0.36</ArmorRating_Blunt>
      <ArmorRating_Heat>0.27</ArmorRating_Heat>
      <Insulation_Cold>1</Insulation_Cold>
      <EquipDelay>5</EquipDelay>
    </statBases>
    <equippedStatOffsets>
      <MoveSpeed>-0.12</MoveSpeed>
    </equippedStatOffsets>
    <thingCategories>
      <li>ApparelArmor</li>
    </thingCategories>
    <costList>
      <Cloth>30</Cloth>
      <Steel>60</Steel>
      <ComponentIndustrial>1</ComponentIndustrial>
    </costList>
    <apparel>
      <bodyPartGroups>
        <li>Torso</li>
        <li>Neck</li>
        <li>Shoulders</li>
        <li>Arms</li>
        <li>Legs</li>
      </bodyPartGroups>
      <wornGraphicPath>Things/Items/Apparel/MIMobileInfantryFlakVest</wornGraphicPath>
      <layers>
        <li>Middle</li>
      </layers>
      <tags>
        <li>IndustrialMilitaryBasic</li>
      </tags>
      <defaultOutfitTags>
        <li>Soldier</li>
      </defaultOutfitTags>
    </apparel>
    <colorGenerator Class="ColorGenerator_Options">
      <options>
        <li>
          <only>(0.33,0.33,0.33)</only>
        </li>
        <li>
          <only>(0.65,0.65,0.65)</only>
        </li>
        <li>
          <weight>0.5</weight>
          <min>(0.3,0.3,0.3)</min>
          <max>(0.5,0.5,0.5)</max>
        </li>
      </options>
    </colorGenerator>
    <tradeTags>
      <li>Armor</li>
    </tradeTags>
  </ThingDef>

<!-- M-1A4 Powered Suit -->

<ThingDef ParentName="ArmorMachineableBase">
    <defName>Fed_Apparel_M-1A4PoweredSuit</defName>
    <label>M-1A4 Powered Suit</label>
    <description>"The M-1A4 Powered Suit is what makes Mobile Infantry truly mobile. Servo-enhanced strength lets you carry heavy weapons like sidearms and shrug off loads that would break an unassisted human. Integrated jump jets—built right into the armor's frame—launch you across terrain in bounding leaps, letting you cover kilometers rapidly while staying 'on the bounce.' The suit's titanium alloy shell stops everything from small arms to bug mandibles, and full environmental sealing means you can operate anywhere—vacuum, toxic atmospheres, radioactive zones.

Heavy? Yes. Slow? Compared to unarmored troops. But when you're sealed in an M-1A4, you're not just a trooper anymore—you're a walking tank with jump jets. One suited trooper can accomplish what takes a full squad in standard armor. The Federation's enemies learned to fear the distinctive 'steel gorilla' silhouette of powered MI troopers. This is the suit that Heinlein envisioned, the armor that defined powered infantry combat. Service guarantees citizenship—but the M-1A4 guarantees you'll survive to earn it."</description>
    <techLevel>Spacer</techLevel>
    <recipeMaker>
      <researchPrerequisite>Research_FederationArmory</researchPrerequisite>
      <unfinishedThingDef>UnfinishedTechArmor</unfinishedThingDef>
      <skillRequirements>
        <Crafting>4</Crafting>
      </skillRequirements>
      <displayPriority>220</displayPriority>
    </recipeMaker>
    <graphicData>
      <texPath>Things/Items/Apparel/M-1A4PoweredArmor_Male_south</texPath>
      <graphicClass>Graphic_Single</graphicClass>
      <drawSize>1.10</drawSize>
    </graphicData>
    <statBases>
      <WorkToMake>75000</WorkToMake>
      <MaxHitPoints>400</MaxHitPoints>
      <Mass>15</Mass>
      <Flammability>0.4</Flammability>
      <ArmorRating_Sharp>1.2</ArmorRating_Sharp>
      <ArmorRating_Blunt>0.5</ArmorRating_Blunt>
      <ArmorRating_Heat>1</ArmorRating_Heat>
      <Insulation_Cold>70</Insulation_Cold>
      <Insulation_Heat>12</Insulation_Heat>
      <EquipDelay>17</EquipDelay>
    </statBases>
    <equippedStatOffsets>
      <ToxicEnvironmentResistance>0.95</ToxicEnvironmentResistance>
      <ToxicResistance>0.95</ToxicResistance>
      <MeleeDamageFactor>0.25</MeleeDamageFactor>
      <CarryingCapacity>15</CarryingCapacity>
      <VacuumResistance MayRequire="Ludeon.RimWorld.Odyssey">0.3</VacuumResistance>
      <MoveSpeed>-0.6</MoveSpeed>
    </equippedStatOffsets>
    <thingCategories>
      <li>ApparelArmor</li>
    </thingCategories>
    <costList>
      <Cloth>30</Cloth>
      <Steel>60</Steel>
      <ComponentIndustrial>1</ComponentIndustrial>
    </costList>
    <comps>
      <li Class="CompProperties_ApparelReloadable">
        <maxCharges>5</maxCharges>
        <ammoDef>Chemfuel</ammoDef>
        <ammoCountPerCharge>20</ammoCountPerCharge>
        <baseReloadTicks>60</baseReloadTicks>
        <soundReload>Standard_Reload</soundReload>
        <hotKey>Misc4</hotKey>
        <chargeNoun>jump</chargeNoun>
        <displayGizmoWhileUndrafted>false</displayGizmoWhileUndrafted>
      </li>
    </comps>
    <verbs>
      <li>
        <verbClass>Verb_Jump</verbClass>
        <label>jump</label>
        <commandIcon>Things/Pawn/Humanlike/Apparel/JumpPack/JumpPack</commandIcon>
        <violent>false</violent>
        <hasStandardCommand>true</hasStandardCommand>
        <onlyManualCast>True</onlyManualCast>
        <forceNormalTimeSpeed>false</forceNormalTimeSpeed>
        <warmupTime>0.5</warmupTime>
        <warmupEffecter>JumpWarmupEffect</warmupEffecter>
        <flightEffecterDef>JumpFlightEffect</flightEffecterDef>
        <requireLineOfSight>true</requireLineOfSight>
        <targetParams>
          <canTargetLocations>true</canTargetLocations>
          <canTargetPawns>false</canTargetPawns>
          <canTargetBuildings>false</canTargetBuildings>
        </targetParams>
      </li>
    </verbs>
    <apparel>
      <bodyPartGroups>
        <li>Torso</li>
        <li>Neck</li>
        <li>Shoulders</li>
        <li>Arms</li>
        <li>Legs</li>
      </bodyPartGroups>
      <wornGraphicPath>Things/Items/Apparel/M-1A4PoweredArmor</wornGraphicPath>
      <layers>
        <li>Middle</li>
        <li>Shell</li>
      </layers>
      <tags>
        <li>IndustrialMilitaryBasic</li>
      </tags>
      <defaultOutfitTags>
        <li>Soldier</li>
      </defaultOutfitTags>
    </apparel>
    <tradeTags>
      <li>Armor</li>
    </tradeTags>
  </ThingDef>

<!-- MI Combat Undersuit -->

<ThingDef ParentName="ApparelMakeableBase">
    <defName>Fed_Apparel_MICombatUndersuit</defName>
    <label>MI Combat Undersuit</label>
    <description>"The MI Combat Undersuit is what troopers actually live in. Black base layer with gray utility coveralls—worn under armor for protection, padding, and moisture control. On ship duty or between operations, many troopers wear just the undersuit without armor. It's not glamorous, but it keeps you comfortable during the long hours sealed inside combat armor. Wash it when you can, wear it till it falls apart."</description>
    <recipeMaker>
      <researchPrerequisite>Research_FederationArmory</researchPrerequisite>
      <displayPriority>205</displayPriority>
    </recipeMaker>
    <graphicData>
      <texPath>Things/Items/Apparel/MICombatUndersuit_Male_south</texPath>
      <graphicClass>Graphic_Single</graphicClass>
      <shaderType>CutoutComplex</shaderType>
    </graphicData>
    <techLevel>Industrial</techLevel>
    <costStuffCount>40</costStuffCount>
    <stuffCategories>
      <li>Fabric</li>
      <li>Leathery</li>
    </stuffCategories>
    <thingCategories>
      <li>ApparelMisc</li>
    </thingCategories>
    <statBases>
      <MaxHitPoints>100</MaxHitPoints>
      <WorkToMake>1600</WorkToMake>
      <Mass>0.25</Mass>
      <StuffEffectMultiplierArmor>0.2</StuffEffectMultiplierArmor>
      <StuffEffectMultiplierInsulation_Cold>0.22</StuffEffectMultiplierInsulation_Cold>
      <StuffEffectMultiplierInsulation_Heat>0.10</StuffEffectMultiplierInsulation_Heat>
      <EquipDelay>1.5</EquipDelay>
    </statBases>
    <apparel>
      <bodyPartGroups>
        <li>Torso</li>
        <li>Legs</li>
        <li>Arms</li>
      </bodyPartGroups>
      <wornGraphicPath>Things/Items/Apparel/MICombatUndersuit</wornGraphicPath>
      <layers>
        <li>OnSkin</li>
      </layers>
      <tags>
        <li>IndustrialBasic</li>
      </tags>
      <defaultOutfitTags>
        <li>Worker</li>
        <li>Soldier</li>
        <li>Spacefarer</li>
      </defaultOutfitTags>
      <canBeDesiredForIdeo>false</canBeDesiredForIdeo>
      <useWornGraphicMask>true</useWornGraphicMask>
    </apparel>
    <colorGenerator Class="ColorGenerator_StandardApparel" />
    <tradeTags>
      <li>BasicClothing</li>
    </tradeTags>
  </ThingDef>

<!-- MI Training Fatigues -->

<ThingDef ParentName="ApparelMakeableBase">
    <defName>Fed_Apparel_MITrainingFatigues</defName>
    <label>MI Training Fatigues</label>
    <description>"The black training fatigues mark you as a boot—a recruit going through hell at Camp Currie or one of the other training facilities. Every Mobile Infantry trooper remembers wearing these during endless PT runs, knife-throwing practice, and Sergeant Zim's brutal close combat drills. The MI wings on your chest mean you're working toward earning the right to wear combat armor. Survive training, and you'll never want to see these fatigues again."</description>
    <recipeMaker>
      <researchPrerequisite>Research_FederationArmory</researchPrerequisite>
      <displayPriority>205</displayPriority>
    </recipeMaker>
    <graphicData>
      <texPath>Things/Items/Apparel/MITrainingFatigues_Male_south</texPath>
      <graphicClass>Graphic_Single</graphicClass>
      <shaderType>CutoutComplex</shaderType>
    </graphicData>
    <techLevel>Industrial</techLevel>
    <costStuffCount>40</costStuffCount>
    <stuffCategories>
      <li>Fabric</li>
      <li>Leathery</li>
    </stuffCategories>
    <thingCategories>
      <li>ApparelMisc</li>
    </thingCategories>
    <statBases>
      <MaxHitPoints>100</MaxHitPoints>
      <WorkToMake>1600</WorkToMake>
      <Mass>0.25</Mass>
      <StuffEffectMultiplierArmor>0.2</StuffEffectMultiplierArmor>
      <StuffEffectMultiplierInsulation_Cold>0.22</StuffEffectMultiplierInsulation_Cold>
      <StuffEffectMultiplierInsulation_Heat>0.10</StuffEffectMultiplierInsulation_Heat>
      <EquipDelay>1.5</EquipDelay>
    </statBases>
    <apparel>
      <bodyPartGroups>
        <li>Torso</li>
        <li>Legs</li>
        <li>Arms</li>
      </bodyPartGroups>
      <wornGraphicPath>Things/Items/Apparel/MITrainingFatigues</wornGraphicPath>
      <layers>
        <li>Middle</li>
      </layers>
      <tags>
        <li>IndustrialBasic</li>
      </tags>
      <defaultOutfitTags>
        <li>Worker</li>
        <li>Soldier</li>
        <li>Spacefarer</li>
      </defaultOutfitTags>
      <canBeDesiredForIdeo>false</canBeDesiredForIdeo>
      <useWornGraphicMask>true</useWornGraphicMask>
    </apparel>
    <colorGenerator Class="ColorGenerator_StandardApparel" />
    <tradeTags>
      <li>BasicClothing</li>
    </tradeTags>
  </ThingDef>

<!-- MI Dress Uniform Mobile infantry -->

<ThingDef ParentName="ApparelMakeableBase">
    <defName>Fed_Apparel_MIDressUniformMobileInfantry</defName>
    <label>MI Dress Uniform Mobile Infantry</label>
    <description>"The MI Dress Uniform is reserved for formal occasions—citizenship ceremonies, funerals for fallen troopers, official Federation functions. When the Mobile Infantry needs to look professional rather than battle-ready, this is what they wear. The black tunic with rank insignia on the shoulders and the white belt represent Federal Service honor. Every trooper keeps dress uniform ready—you never know when you'll need to bury a friend or accept a medal."</description>
    <recipeMaker>
      <researchPrerequisite>Research_FederationArmory</researchPrerequisite>
      <displayPriority>205</displayPriority>
    </recipeMaker>
    <graphicData>
      <texPath>Things/Items/Apparel/MIDressUniformMobileInfantry_Male_south</texPath>
      <graphicClass>Graphic_Single</graphicClass>
      <shaderType>CutoutComplex</shaderType>
    </graphicData>
    <techLevel>Industrial</techLevel>
    <costStuffCount>40</costStuffCount>
    <stuffCategories>
      <li>Fabric</li>
      <li>Leathery</li>
    </stuffCategories>
    <thingCategories>
      <li>ApparelMisc</li>
    </thingCategories>
    <statBases>
      <MaxHitPoints>100</MaxHitPoints>
      <WorkToMake>1600</WorkToMake>
      <Mass>0.25</Mass>
      <StuffEffectMultiplierArmor>0.2</StuffEffectMultiplierArmor>
      <StuffEffectMultiplierInsulation_Cold>0.22</StuffEffectMultiplierInsulation_Cold>
      <StuffEffectMultiplierInsulation_Heat>0.10</StuffEffectMultiplierInsulation_Heat>
      <EquipDelay>1.5</EquipDelay>
    </statBases>
    <apparel>
      <bodyPartGroups>
        <li>Torso</li>
        <li>Legs</li>
        <li>Arms</li>
      </bodyPartGroups>
      <wornGraphicPath>Things/Items/Apparel/MIDressUniformMobileInfantry</wornGraphicPath>
      <layers>
        <li>Middle</li>
        <li>Shell</li>
      </layers>
      <tags>
        <li>IndustrialBasic</li>
      </tags>
      <defaultOutfitTags>
        <li>Worker</li>
        <li>Soldier</li>
        <li>Spacefarer</li>
      </defaultOutfitTags>
      <canBeDesiredForIdeo>false</canBeDesiredForIdeo>
      <useWornGraphicMask>true</useWornGraphicMask>
    </apparel>
    <colorGenerator Class="ColorGenerator_StandardApparel" />
    <tradeTags>
      <li>BasicClothing</li>
    </tradeTags>
  </ThingDef>

<!-- Fleet Officer Dress Uniform -->

<ThingDef ParentName="ApparelMakeableBase">
    <defName>Fed_Apparel_FleetOfficerDressUniform</defName>
    <label>Fleet Officer Dress Uniform</label>
    <description>"Fleet officers wear light blue gray where Mobile Infantry wears gray. The light blue gray tunic with its distinctive lapels marks you as Federation Navy—starship pilots, navigation specialists, and fleet command. While MI troopers fight bugs on the ground, Fleet officers control the spaceways and drop those troopers into combat zones. The gray uniform represents a different kind of service, but service all the same. Would you like to know more about joining Fleet?"</description>
    <recipeMaker>
      <researchPrerequisite>Research_FederationArmory</researchPrerequisite>
      <displayPriority>205</displayPriority>
    </recipeMaker>
    <graphicData>
      <texPath>Things/Items/Apparel/FleetOfficerDressUniform_Male_south</texPath>
      <graphicClass>Graphic_Single</graphicClass>
      <shaderType>CutoutComplex</shaderType>
    </graphicData>
    <techLevel>Industrial</techLevel>
    <costStuffCount>40</costStuffCount>
    <stuffCategories>
      <li>Fabric</li>
      <li>Leathery</li>
    </stuffCategories>
    <thingCategories>
      <li>ApparelMisc</li>
    </thingCategories>
    <statBases>
      <MaxHitPoints>100</MaxHitPoints>
      <WorkToMake>1600</WorkToMake>
      <Mass>0.25</Mass>
      <StuffEffectMultiplierArmor>0.2</StuffEffectMultiplierArmor>
      <StuffEffectMultiplierInsulation_Cold>0.22</StuffEffectMultiplierInsulation_Cold>
      <StuffEffectMultiplierInsulation_Heat>0.10</StuffEffectMultiplierInsulation_Heat>
      <EquipDelay>1.5</EquipDelay>
    </statBases>
    <apparel>
      <bodyPartGroups>
        <li>Torso</li>
        <li>Legs</li>
        <li>Arms</li>
      </bodyPartGroups>
      <wornGraphicPath>Things/Items/Apparel/FleetOfficerDressUniform</wornGraphicPath>
      <layers>
        <li>Middle</li>
        <li>Shell</li>
      </layers>
      <tags>
        <li>IndustrialBasic</li>
      </tags>
      <defaultOutfitTags>
        <li>Worker</li>
        <li>Soldier</li>
        <li>Spacefarer</li>
      </defaultOutfitTags>
      <canBeDesiredForIdeo>false</canBeDesiredForIdeo>
      <useWornGraphicMask>true</useWornGraphicMask>
    </apparel>
    <tradeTags>
      <li>BasicClothing</li>
    </tradeTags>
  </ThingDef>

<!-- Secret Intelligence Service Uniform -->

<ThingDef ParentName="ApparelMakeableBase">
    <defName>Fed_Apparel_SecretIntelligenceServiceUniform</defName>
    <label>Secret Intelligence Service Uniform</label>
    <description>Intel has its own group of psychics called Psi Ops as a core and leadership branch and often utilizes them to collect data. Intel also calculates casualties and survival rates. However, Intel is rarely correct, such as at the Battle of Klendathu where Intel believed that the plasma fired at the ships was "only random and light"; a fact that was proven wrong when many shots of plasma tore through the hulls of Fleet's ships. Intel values information more than human life and has an uneasy relationship with other branches. Intel often conducts high-priority top-secret missions of which commanders in other branches are unaware such as the development of the bio-engineered X-Bug as part of an offensive against the Arachnids on the planet Hesperus.</description>
    <recipeMaker>
      <researchPrerequisite>Research_FederationArmory</researchPrerequisite>
      <displayPriority>205</displayPriority>
    </recipeMaker>
    <graphicData>
      <texPath>Things/Items/Apparel/SecretIntelligenceServiceUniform_Male_south</texPath>
      <graphicClass>Graphic_Single</graphicClass>
      <shaderType>CutoutComplex</shaderType>
    </graphicData>
    <techLevel>Industrial</techLevel>
    <costStuffCount>40</costStuffCount>
    <stuffCategories>
      <li>Fabric</li>
      <li>Leathery</li>
    </stuffCategories>
    <thingCategories>
      <li>ApparelMisc</li>
    </thingCategories>
    <statBases>
      <MaxHitPoints>100</MaxHitPoints>
      <WorkToMake>1600</WorkToMake>
      <Mass>0.25</Mass>
      <StuffEffectMultiplierArmor>0.2</StuffEffectMultiplierArmor>
      <StuffEffectMultiplierInsulation_Cold>0.22</StuffEffectMultiplierInsulation_Cold>
      <StuffEffectMultiplierInsulation_Heat>0.10</StuffEffectMultiplierInsulation_Heat>
      <EquipDelay>1.5</EquipDelay>
    </statBases>
    <apparel>
      <bodyPartGroups>
        <li>Torso</li>
        <li>Legs</li>
        <li>Arms</li>
      </bodyPartGroups>
      <wornGraphicPath>Things/Items/Apparel/SecretIntelligenceServiceUniform</wornGraphicPath>
      <layers>
        <li>Middle</li>
      </layers>
      <tags>
        <li>IndustrialBasic</li>
      </tags>
      <defaultOutfitTags>
        <li>Worker</li>
        <li>Soldier</li>
        <li>Spacefarer</li>
      </defaultOutfitTags>
      <canBeDesiredForIdeo>false</canBeDesiredForIdeo>
      <useWornGraphicMask>true</useWornGraphicMask>
    </apparel>
    <tradeTags>
      <li>BasicClothing</li>
    </tradeTags>
  </ThingDef>

<!--__Webbings__-->

<ApparelLayerDef> 
         <defName>WebbingLayer</defName> 
         <label>webbing layer</label> 
       <drawOrder>250</drawOrder> 
    </ApparelLayerDef> 

<!-- MI Mobile Infantry Tactical Webbing -->

<ThingDef ParentName="ApparelBase">
    <defName>Fed_Apparel_MIMobileInfantryTacticalWebbing</defName>
    <label>MI Mobile infantry Tactical Webbing</label>
    <description>"A webbing carries the essentials—nothing more, nothing less. Ammunition, grenades, survival kit, sidearm. Every ounce counts when you're operating ahead of the main force. Light, functional, and built to keep you moving."</description>
    <techLevel>Spacer</techLevel>
    <recipeMaker>
      <unfinishedThingDef>UnfinishedPack</unfinishedThingDef>
      <researchPrerequisite>Research_FederationArmory</researchPrerequisite>
      <recipeUsers>
        <li>TableMachining</li>
      </recipeUsers>
      <useIngredientsForColor>false</useIngredientsForColor>
      <workSpeedStat>GeneralLaborSpeed</workSpeedStat>
      <workSkill>Crafting</workSkill>
      <effectWorking>Smith</effectWorking>
      <soundWorking>Recipe_Smith</soundWorking>
      <skillRequirements>
        <Crafting>3</Crafting>
      </skillRequirements>
      <displayPriority>310</displayPriority>
    </recipeMaker>
    <costList>
      <ComponentIndustrial>1</ComponentIndustrial>
      <Steel>20</Steel>
      <Chemfuel>40</Chemfuel>
    </costList>
    <equippedStatOffsets>
      <CarryingCapacity>20</CarryingCapacity>
    </equippedStatOffsets>
    <graphicData>
      <texPath>Things/Items/Apparel/MIMobileInfantryTacticalWebbing_Male_south</texPath>
      <graphicClass>Graphic_Single</graphicClass>
      <drawSize>0.75</drawSize>
    </graphicData>
    <tickerType>Normal</tickerType>
    <statBases>
      <WorkToMake>3600</WorkToMake>
      <Mass>3</Mass>
      <Flammability>0.4</Flammability>
      <PackRadius>4.9</PackRadius>
      <EquipDelay>2</EquipDelay>
    </statBases>
    <thingCategories>
      <li>ApparelUtility</li>
    </thingCategories>
    <generateAllowChance>0.15</generateAllowChance>
    <apparel>
      <wornGraphicPath>Things/Items/Apparel/MIMobileInfantryTacticalWebbing</wornGraphicPath>
      <countsAsClothingForNudity>false</countsAsClothingForNudity>
      <careIfWornByCorpse>false</careIfWornByCorpse>
      <careIfDamaged>false</careIfDamaged>
      <wearPerDay>0</wearPerDay>
      <bodyPartGroups>
        <li>Waist</li>
      </bodyPartGroups>
      <layers>
        <li>WebbingLayer</li>
      </layers>
      <tags>
        <li>Webbings</li>
      </tags>
    </apparel>
    <tradeTags>
      <li>Clothing</li>
      <li>Armor</li>
    </tradeTags>
  </ThingDef>

<!-- MI Mobile Infantry Combat Medic -->

<ThingDef ParentName="ApparelBase">
    <defName>Fed_Apparel_MIMobileInfantryCombatMedic</defName>
    <label>MI Mobile infantry Combat Medic</label>
    <description>The Medical Corps is the force within Federal Armed Services charged with the training and deployment of Medical personnel along with relevant equipment. The Medical Corps' most notable units are those of Combat Medics whom are regularly seen along Mobile Infantry units. It functions alongside both the Mobile Infantry and the Fleet</description>
    <techLevel>Spacer</techLevel>
    <recipeMaker>
      <unfinishedThingDef>UnfinishedPack</unfinishedThingDef>
      <researchPrerequisite>Research_FederationArmory</researchPrerequisite>
      <recipeUsers>
        <li>TableMachining</li>
      </recipeUsers>
      <useIngredientsForColor>false</useIngredientsForColor>
      <workSpeedStat>GeneralLaborSpeed</workSpeedStat>
      <workSkill>Crafting</workSkill>
      <effectWorking>Smith</effectWorking>
      <soundWorking>Recipe_Smith</soundWorking>
      <skillRequirements>
        <Crafting>3</Crafting>
      </skillRequirements>
      <displayPriority>310</displayPriority>
    </recipeMaker>
    <equippedStatOffsets>
      <CarryingCapacity>20</CarryingCapacity>
    </equippedStatOffsets>
    <costList>
      <ComponentIndustrial>1</ComponentIndustrial>
      <Steel>20</Steel>
      <Chemfuel>40</Chemfuel>
    </costList>
    <graphicData>
      <texPath>Things/Items/Apparel/MIMobileInfantryTacticalWebbing_Male_south</texPath>
      <graphicClass>Graphic_Single</graphicClass>
      <drawSize>0.75</drawSize>
    </graphicData>
    <tickerType>Normal</tickerType>
    <statBases>
      <WorkToMake>3600</WorkToMake>
      <Mass>3</Mass>
      <Flammability>0.4</Flammability>
      <PackRadius>4.9</PackRadius>
      <EquipDelay>2</EquipDelay>
    </statBases>
    <thingCategories>
      <li>ApparelUtility</li>
    </thingCategories>
    <generateAllowChance>0.15</generateAllowChance>
    <apparel>
      <wornGraphicPath>Things/Items/Apparel/MIMobileInfantryTacticalWebbing</wornGraphicPath>
      <countsAsClothingForNudity>false</countsAsClothingForNudity>
      <careIfWornByCorpse>false</careIfWornByCorpse>
      <careIfDamaged>false</careIfDamaged>
      <wearPerDay>0</wearPerDay>
      <bodyPartGroups>
        <li>Torso</li>
      </bodyPartGroups>
      <layers>
        <li>WebbingLayer</li>
      </layers>
      <tags>
        <li>Webbing</li>
      </tags>
    </apparel>
    <tradeTags>
      <li>Clothing</li>
      <li>Armor</li>
    </tradeTags>
  </ThingDef>

<!-- MI Mobile Infantry Radio Operator -->

<ThingDef ParentName="ApparelBase">
    <defName>Fed_Apparel_MIMobileInfantryRadioOperator</defName>
    <label>MI Mobile infantry Radio Operator</label>
    <description>A crucial comms specialist, typically carrying a backpack radio to coordinate with command, call in air/orbital support, request reinforcements, and sometimes boost nearby allies' fire rate, ensuring vital communication for massive assaults and strategic maneuvers, though often staying behind front lines for safety while linking infantry pushes</description>
    <techLevel>Spacer</techLevel>
    <recipeMaker>
      <unfinishedThingDef>UnfinishedPack</unfinishedThingDef>
      <researchPrerequisite>Research_FederationArmory</researchPrerequisite>
      <recipeUsers>
        <li>TableMachining</li>
      </recipeUsers>
      <useIngredientsForColor>false</useIngredientsForColor>
      <workSpeedStat>GeneralLaborSpeed</workSpeedStat>
      <workSkill>Crafting</workSkill>
      <effectWorking>Smith</effectWorking>
      <soundWorking>Recipe_Smith</soundWorking>
      <skillRequirements>
        <Crafting>3</Crafting>
      </skillRequirements>
      <displayPriority>310</displayPriority>
    </recipeMaker>
    <equippedStatOffsets>
      <CarryingCapacity>20</CarryingCapacity>
    </equippedStatOffsets>
    <costList>
      <ComponentIndustrial>1</ComponentIndustrial>
      <Steel>20</Steel>
      <Chemfuel>40</Chemfuel>
    </costList>
    <graphicData>
      <texPath>Things/Items/Apparel/MIMobileInfantryTacticalWebbing_Male_south</texPath>
      <graphicClass>Graphic_Single</graphicClass>
      <drawSize>0.75</drawSize>
    </graphicData>
    <tickerType>Normal</tickerType>
    <statBases>
      <WorkToMake>3600</WorkToMake>
      <Mass>3</Mass>
      <Flammability>0.4</Flammability>
      <PackRadius>4.9</PackRadius>
      <EquipDelay>2</EquipDelay>
    </statBases>
    <thingCategories>
      <li>ApparelUtility</li>
    </thingCategories>
    <generateAllowChance>0.15</generateAllowChance>
    <apparel>
      <wornGraphicPath>Things/Items/Apparel/MIMobileInfantryTacticalWebbing</wornGraphicPath>
      <countsAsClothingForNudity>false</countsAsClothingForNudity>
      <careIfWornByCorpse>false</careIfWornByCorpse>
      <careIfDamaged>false</careIfDamaged>
      <wearPerDay>0</wearPerDay>
      <bodyPartGroups>
        <li>Torso</li>
      </bodyPartGroups>
      <layers>
        <li>WebbingLayer</li>
      </layers>
      <tags>
        <li>Webbing</li>
      </tags>
    </apparel>
    <tradeTags>
      <li>Clothing</li>
      <li>Armor</li>
    </tradeTags>
  </ThingDef>

</Defs>